supply_chain_rekor_monitor/CODEOWNERS
supply_chain_rekor_monitor/CONTRIBUTING.md
supply_chain_rekor_monitor/LICENSE
supply_chain_rekor_monitor/SECURITY.md
supply_chain_rekor_monitor/__init__.py
supply_chain_rekor_monitor/artifact.bundle
supply_chain_rekor_monitor/artifact.md
supply_chain_rekor_monitor/bandit-final.txt
supply_chain_rekor_monitor/bandit-initial.txt
supply_chain_rekor_monitor/checkpoint.json
supply_chain_rekor_monitor/main.py
supply_chain_rekor_monitor/merkle_proof.py
supply_chain_rekor_monitor/mypy.final.txt
supply_chain_rekor_monitor/mypy.initial.txt
supply_chain_rekor_monitor/poetry.lock
supply_chain_rekor_monitor/pylint.final.txt
supply_chain_rekor_monitor/pylint.initial.txt
supply_chain_rekor_monitor/ruff.final.txt
supply_chain_rekor_monitor/ruff.initial.text
supply_chain_rekor_monitor/util.py
supply_chain_rekor_monitor-4.1.0.dist-info/METADATA
supply_chain_rekor_monitor-4.1.0.dist-info/WHEEL
supply_chain_rekor_monitor-4.1.0.dist-info/entry_points.txt
supply_chain_rekor_monitor-4.1.0.dist-info/RECORD
