Metadata-Version: 2.1
Name: supply-chain-rekor-monitor
Version: 4.1.0
Summary: This project can be used to verify inclusion of artifacts, whether a correct signature is present, or verify consistency in regards to the Rekor transparency logs.
License: Apache 2.0
Author: cp-57
Author-email: 109479938+cp-57@users.noreply.github.com
Requires-Python: >=3.9,<4.0
Classifier: License :: Other/Proprietary License
Classifier: Programming Language :: Python :: 3
Classifier: Programming Language :: Python :: 3.9
Classifier: Programming Language :: Python :: 3.10
Classifier: Programming Language :: Python :: 3.11
Classifier: Programming Language :: Python :: 3.12
Classifier: Programming Language :: Python :: 3.13
Requires-Dist: cryptography (>=43.0.3,<44.0.0)
Requires-Dist: jsonschema (>=4.23.0,<5.0.0)
Requires-Dist: requests (>=2.32.3,<3.0.0)
